TP_V_09_03/add_1_bit.v
module add_1_bit (e1, e2, r0, s, r1);
    input e1;
    input e2;
    input r0;
    output s;
    output r1;


    assign r1 = (e1 & e2) | (e1 & r0) | (e2 & r0);
    assign s = e1 ^ e2 ^ r0;

endmodule


//module reg_lin(X, s):



//end module

TP_V_09_03/test_add_1_bit.v
`timescale 1ns / 1ps
module stimulus;
	// Inputs
	reg x;
	reg y;
	reg r;
	// Outputs
	wire z;
	wire r1;
	// Instantiate the Unit Under Test (UUT)
	add_1_bit uut (
		x, 
		y,
		r,
		z,
		r1
	);
 
	initial begin
	$dumpfile("add_1_bit_test.vcd");
    $dumpvars(0,stimulus);
		// Initialize Inputs
		x = 0;
		y = 0;
		r = 0;
 
	#20 y = 1;
	#20 x = 1;
	#20 y = 0;
	#20 r = 1;	
	#20 y = 1;
	#20 x = 0;
	#20 y = 0;  
	#40 ;
 
	end  
 
		initial begin
		 $monitor("t=%3d r0=%d x=%d,y=%d, \tz=%d, r1=%d \n",$time,r,x,y,z,r1, );
		 end
 
endmodule

TP_V_09_03/add_1_bit_test.vcd
$date
	Thu Mar 09 13:56:05 2023
$end
$version
	Icarus Verilog
$end
$timescale
	1ps
$end
$scope module stimulus $end
$var wire 1 ! z $end
$var wire 1 " r1 $end
$var reg 1 # r $end
$var reg 1 $ x $end
$var reg 1 % y $end
$scope module uut $end
$var wire 1 $ e1 $end
$var wire 1 % e2 $end
$var wire 1 # r0 $end
$var wire 1 " r1 $end
$var wire 1 ! s $end
$upscope $end
$upscope $end
$enddefinitions $end
$comment Show the parameter values. $end
$dumpall
$end
#0
$dumpvars
0%
0$
0#
0"
0!
$end
#20000
1!
1%
#40000
1"
0!
1$
#60000
0"
1!
0%
#80000
1"
0!
1#
#100000
1!
1%
#120000
0!
0$
#140000
0"
1!
0%
