TP_V_09_03/and_gate3.v
module and_gate3 (e1, e2, e3, s);
    input e1;
    input e2;
    input e3;
    output s;


    assign s = e1 & e2 & e3;

endmodule


//module reg_lin(X, s):



//end module

TP_V_09_03/test_and_gate3.v
`timescale 1ns / 1ps
module stimulus;
	// Inputs
	reg w;
	reg x;
	reg y;
	// Outputs
	wire z;
	// Instantiate the Unit Under Test (UUT)
	and_gate3 uut (
		w,
		x, 
		y, 
		z
	);
 
	initial begin
	$dumpfile("and_test3.vcd");
    $dumpvars(0,stimulus);
		// Initialize Inputs
		w = 0;
		x = 0;
		y = 0;
 
	#20 y = 1;
	#20 x = 1;
	#20 y = 0;
	#20 w = 1;	
	#20 y = 1;
	#20 x = 0;
	#20 y = 0;	  
	#40 ;
 
	end  
 
		initial begin
		 $monitor("t=%3d w=%d x=%d,y=%d,z=%d \n",$time,w,x,y,z, );
		 end
 
endmodule

TP_V_09_03/and_test3.vcd
$date
	Thu Mar 09 12:43:37 2023
$end
$version
	Icarus Verilog
$end
$timescale
	1ps
$end
$scope module stimulus $end
$var wire 1 ! z $end
$var reg 1 " w $end
$var reg 1 # x $end
$var reg 1 $ y $end
$scope module uut $end
$var wire 1 " e1 $end
$var wire 1 # e2 $end
$var wire 1 $ e3 $end
$var wire 1 ! s $end
$upscope $end
$upscope $end
$enddefinitions $end
$comment Show the parameter values. $end
$dumpall
$end
#0
$dumpvars
0$
0#
0"
0!
$end
#20000
1$
#40000
1#
#60000
0$
#80000
1"
#100000
1!
1$
#120000
0!
0#
#140000
0$
